vidtoolz_trim/__init__.py
vidtoolz_trim-0.1.2.dist-info/licenses/LICENSE
vidtoolz_trim-0.1.2.dist-info/METADATA
vidtoolz_trim-0.1.2.dist-info/WHEEL
vidtoolz_trim-0.1.2.dist-info/entry_points.txt
vidtoolz_trim-0.1.2.dist-info/top_level.txt
vidtoolz_trim-0.1.2.dist-info/RECORD
