Metadata-Version: 2.4
Name: vidtoolz-trim
Version: 0.1.2
Summary: Trim video using ffmpeg
Author: Sukhbinder Singh
License: Apache-2.0
Project-URL: Homepage, https://github.com/sukhbinder/vidtoolz-trim
Project-URL: Changelog, https://github.com/sukhbinder/vidtoolz-trim/releases
Project-URL: Issues, https://github.com/sukhbinder/vidtoolz-trim/issues
Project-URL: CI, https://github.com/sukhbinder/vidtoolz-trim/actions
Classifier: License :: OSI Approved :: Apache Software License
License-File: LICENSE
Requires-Dist: vidtoolz
Provides-Extra: test
Requires-Dist: pytest; extra == "test"
Dynamic: license-file
